shruti/__init__.py
shruti/nemo/__init__.py
shruti/nemo/collections/__init__.py
shruti/nemo/collections/asr/README.md
shruti/nemo/collections/asr/__init__.py
shruti/nemo/collections/asr/data/__init__.py
shruti/nemo/collections/asr/data/audio_to_audio.py
shruti/nemo/collections/asr/data/audio_to_audio_dataset.py
shruti/nemo/collections/asr/data/audio_to_ctm_dataset.py
shruti/nemo/collections/asr/data/audio_to_diar_label.py
shruti/nemo/collections/asr/data/audio_to_label.py
shruti/nemo/collections/asr/data/audio_to_label_dataset.py
shruti/nemo/collections/asr/data/audio_to_text.py
shruti/nemo/collections/asr/data/audio_to_text_dali.py
shruti/nemo/collections/asr/data/audio_to_text_dataset.py
shruti/nemo/collections/asr/data/audio_to_text_lhotse.py
shruti/nemo/collections/asr/data/audio_to_text_lhotse_prompted.py
shruti/nemo/collections/asr/data/data_simulation.py
shruti/nemo/collections/asr/data/feature_to_label.py
shruti/nemo/collections/asr/data/feature_to_label_dataset.py
shruti/nemo/collections/asr/data/feature_to_text.py
shruti/nemo/collections/asr/data/feature_to_text_dataset.py
shruti/nemo/collections/asr/data/huggingface/__init__.py
shruti/nemo/collections/asr/data/huggingface/hf_audio_to_text.py
shruti/nemo/collections/asr/data/huggingface/hf_audio_to_text_dataset.py
shruti/nemo/collections/asr/data/text_to_text.py
shruti/nemo/collections/asr/losses/__init__.py
shruti/nemo/collections/asr/losses/angularloss.py
shruti/nemo/collections/asr/losses/audio_losses.py
shruti/nemo/collections/asr/losses/bce_loss.py
shruti/nemo/collections/asr/losses/ctc.py
shruti/nemo/collections/asr/losses/lattice_losses.py
shruti/nemo/collections/asr/losses/rnnt.py
shruti/nemo/collections/asr/losses/rnnt_pytorch.py
shruti/nemo/collections/asr/losses/ssl_losses/__init__.py
shruti/nemo/collections/asr/losses/ssl_losses/contrastive.py
shruti/nemo/collections/asr/losses/ssl_losses/ctc.py
shruti/nemo/collections/asr/losses/ssl_losses/mlm.py
shruti-0.1.1.dist-info/WHEEL
shruti-0.1.1.dist-info/METADATA
shruti-0.1.1.dist-info/RECORD
